{"path":[	{"x":303, "y":724},
	{"x":303, "y":725},
	{"x":303, "y":726},
	{"x":304, "y":724},
	{"x":304, "y":725},
	{"x":304, "y":726},
	{"x":305, "y":724},
	{"x":305, "y":725},
	{"x":305, "y":726},
	{"x":306, "y":724},
	{"x":306, "y":725},
	{"x":306, "y":726},
	{"x":307, "y":724},
	{"x":307, "y":725},
	{"x":307, "y":726},
	{"x":308, "y":724},
	{"x":308, "y":725},
	{"x":308, "y":726},
	{"x":309, "y":724},
	{"x":309, "y":725},
	{"x":309, "y":726},
	{"x":310, "y":724},
	{"x":310, "y":725},
	{"x":310, "y":726},
	{"x":311, "y":724},
	{"x":311, "y":725},
	{"x":311, "y":726},
	{"x":312, "y":724},
	{"x":312, "y":725},
	{"x":312, "y":726},
	{"x":313, "y":724},
	{"x":313, "y":725},
	{"x":313, "y":726},
	{"x":314, "y":723},
	{"x":314, "y":724},
	{"x":314, "y":725},
	{"x":315, "y":723},
	{"x":315, "y":724},
	{"x":315, "y":725},
	{"x":316, "y":723},
	{"x":316, "y":724},
	{"x":316, "y":725},
	{"x":317, "y":723},
	{"x":317, "y":724},
	{"x":317, "y":725},
	{"x":318, "y":723},
	{"x":318, "y":724},
	{"x":318, "y":725},
	{"x":319, "y":723},
	{"x":319, "y":724},
	{"x":319, "y":725},
	{"x":320, "y":723},
	{"x":320, "y":724},
	{"x":320, "y":725},
	{"x":321, "y":723},
	{"x":321, "y":724},
	{"x":321, "y":725},
	{"x":322, "y":723},
	{"x":322, "y":724},
	{"x":322, "y":725},
	{"x":323, "y":723},
	{"x":323, "y":724},
	{"x":323, "y":725},
	{"x":324, "y":723},
	{"x":324, "y":724},
	{"x":324, "y":725},
	{"x":325, "y":723},
	{"x":325, "y":724},
	{"x":325, "y":725},
	{"x":326, "y":723},
	{"x":326, "y":724},
	{"x":326, "y":725},
	{"x":327, "y":723},
	{"x":327, "y":724},
	{"x":327, "y":725},
	{"x":328, "y":723},
	{"x":328, "y":724},
	{"x":328, "y":725},
	{"x":329, "y":723},
	{"x":329, "y":724},
	{"x":329, "y":725},
	{"x":330, "y":723},
	{"x":330, "y":724},
	{"x":330, "y":725},
	{"x":331, "y":723},
	{"x":331, "y":724},
	{"x":331, "y":725},
	{"x":332, "y":723},
	{"x":332, "y":724},
	{"x":332, "y":725},
	{"x":333, "y":722},
	{"x":333, "y":723},
	{"x":333, "y":724},
	{"x":334, "y":722},
	{"x":334, "y":723},
	{"x":334, "y":724},
	{"x":335, "y":722},
	{"x":335, "y":723},
	{"x":335, "y":724},
	{"x":336, "y":722},
	{"x":336, "y":723},
	{"x":336, "y":724},
	{"x":337, "y":722},
	{"x":337, "y":723},
	{"x":337, "y":724},
	{"x":338, "y":722},
	{"x":338, "y":723},
	{"x":338, "y":724},
	{"x":339, "y":722},
	{"x":339, "y":723},
	{"x":339, "y":724},
	{"x":340, "y":722},
	{"x":340, "y":723},
	{"x":340, "y":724},
	{"x":341, "y":722},
	{"x":341, "y":723},
	{"x":341, "y":724},
	{"x":342, "y":722},
	{"x":342, "y":723},
	{"x":342, "y":724},
	{"x":343, "y":722},
	{"x":343, "y":723},
	{"x":343, "y":724},
	{"x":344, "y":722},
	{"x":344, "y":723},
	{"x":344, "y":724},
	{"x":345, "y":722},
	{"x":345, "y":723},
	{"x":345, "y":724},
	{"x":346, "y":722},
	{"x":346, "y":723},
	{"x":346, "y":724},
	{"x":347, "y":722},
	{"x":347, "y":723},
	{"x":347, "y":724},
	{"x":348, "y":722},
	{"x":348, "y":723},
	{"x":348, "y":724},
	{"x":349, "y":722},
	{"x":349, "y":723},
	{"x":349, "y":724},
	{"x":350, "y":722},
	{"x":350, "y":723},
	{"x":350, "y":724},
	{"x":351, "y":722},
	{"x":351, "y":723},
	{"x":352, "y":721},
	{"x":352, "y":722},
	{"x":352, "y":723},
	{"x":353, "y":721},
	{"x":353, "y":722},
	{"x":353, "y":723},
	{"x":354, "y":721},
	{"x":354, "y":722},
	{"x":354, "y":723},
	{"x":355, "y":721},
	{"x":355, "y":722},
	{"x":355, "y":723},
	{"x":356, "y":721},
	{"x":356, "y":722},
	{"x":356, "y":723},
	{"x":357, "y":721},
	{"x":357, "y":722},
	{"x":357, "y":723},
	{"x":358, "y":721},
	{"x":358, "y":722},
	{"x":358, "y":723},
	{"x":359, "y":721},
	{"x":359, "y":722},
	{"x":359, "y":723},
	{"x":360, "y":721},
	{"x":360, "y":722},
	{"x":360, "y":723},
	{"x":361, "y":721},
	{"x":361, "y":722},
	{"x":361, "y":723},
	{"x":362, "y":721},
	{"x":362, "y":722},
	{"x":362, "y":723},
	{"x":363, "y":721},
	{"x":363, "y":722},
	{"x":363, "y":723},
	{"x":364, "y":721},
	{"x":364, "y":722},
	{"x":364, "y":723},
	{"x":365, "y":721},
	{"x":365, "y":722},
	{"x":365, "y":723},
	{"x":366, "y":721},
	{"x":366, "y":722},
	{"x":366, "y":723},
	{"x":367, "y":721},
	{"x":367, "y":722},
	{"x":367, "y":723},
	{"x":368, "y":721},
	{"x":368, "y":722},
	{"x":368, "y":723},
	{"x":369, "y":721},
	{"x":369, "y":722},
	{"x":369, "y":723},
	{"x":370, "y":720},
	{"x":370, "y":721},
	{"x":370, "y":722},
	{"x":371, "y":720},
	{"x":371, "y":721},
	{"x":371, "y":722},
	{"x":372, "y":720},
	{"x":372, "y":721},
	{"x":372, "y":722},
	{"x":373, "y":720},
	{"x":373, "y":721},
	{"x":373, "y":722},
	{"x":374, "y":720},
	{"x":374, "y":721},
	{"x":374, "y":722},
	{"x":375, "y":720},
	{"x":375, "y":721},
	{"x":375, "y":722},
	{"x":376, "y":720},
	{"x":376, "y":721},
	{"x":376, "y":722},
	{"x":377, "y":720},
	{"x":377, "y":721},
	{"x":377, "y":722},
	{"x":378, "y":720},
	{"x":378, "y":721},
	{"x":378, "y":722},
	{"x":379, "y":720},
	{"x":379, "y":721},
	{"x":379, "y":722},
	{"x":380, "y":720},
	{"x":380, "y":721},
	{"x":380, "y":722},
	{"x":381, "y":720},
	{"x":381, "y":721},
	{"x":381, "y":722},
	{"x":382, "y":720},
	{"x":382, "y":721},
	{"x":382, "y":722},
	{"x":383, "y":720},
	{"x":383, "y":721},
	{"x":383, "y":722},
	{"x":384, "y":720},
	{"x":384, "y":721},
	{"x":384, "y":722},
	{"x":385, "y":720},
	{"x":385, "y":721},
	{"x":385, "y":722},
	{"x":386, "y":720},
	{"x":386, "y":721},
	{"x":386, "y":722},
	{"x":387, "y":720},
	{"x":387, "y":721},
	{"x":387, "y":722},
	{"x":388, "y":720},
	{"x":388, "y":721},
	{"x":388, "y":722},
	{"x":389, "y":719},
	{"x":389, "y":720},
	{"x":389, "y":721},
	{"x":390, "y":719},
	{"x":390, "y":720},
	{"x":390, "y":721},
	{"x":391, "y":719},
	{"x":391, "y":720},
	{"x":391, "y":721},
	{"x":392, "y":719},
	{"x":392, "y":720},
	{"x":392, "y":721},
	{"x":393, "y":719},
	{"x":393, "y":720},
	{"x":393, "y":721},
	{"x":394, "y":719},
	{"x":394, "y":720},
	{"x":394, "y":721},
	{"x":395, "y":719},
	{"x":395, "y":720},
	{"x":395, "y":721},
	{"x":396, "y":719},
	{"x":396, "y":720},
	{"x":396, "y":721},
	{"x":397, "y":719},
	{"x":397, "y":720},
	{"x":397, "y":721},
	{"x":398, "y":719},
	{"x":398, "y":720},
	{"x":398, "y":721},
	{"x":399, "y":719},
	{"x":399, "y":720},
	{"x":399, "y":721},
	{"x":400, "y":719},
	{"x":400, "y":720},
	{"x":400, "y":721},
	{"x":401, "y":719},
	{"x":401, "y":720},
	{"x":401, "y":721},
	{"x":402, "y":719},
	{"x":402, "y":720},
	{"x":402, "y":721},
	{"x":403, "y":719},
	{"x":403, "y":720},
	{"x":403, "y":721},
	{"x":404, "y":719},
	{"x":404, "y":720},
	{"x":404, "y":721},
	{"x":405, "y":719},
	{"x":405, "y":720},
	{"x":405, "y":721},
	{"x":406, "y":719},
	{"x":406, "y":720},
	{"x":406, "y":721},
	{"x":407, "y":719},
	{"x":407, "y":720},
	{"x":407, "y":721},
	{"x":408, "y":718},
	{"x":408, "y":719},
	{"x":408, "y":720},
	{"x":409, "y":718},
	{"x":409, "y":719},
	{"x":409, "y":720},
	{"x":410, "y":718},
	{"x":410, "y":719},
	{"x":410, "y":720},
	{"x":411, "y":718},
	{"x":411, "y":719},
	{"x":411, "y":720},
	{"x":412, "y":718},
	{"x":412, "y":719},
	{"x":412, "y":720},
	{"x":413, "y":718},
	{"x":413, "y":719},
	{"x":413, "y":720},
	{"x":414, "y":718},
	{"x":414, "y":719},
	{"x":414, "y":720},
	{"x":415, "y":718},
	{"x":415, "y":719},
	{"x":415, "y":720},
	{"x":416, "y":718},
	{"x":416, "y":719},
	{"x":416, "y":720},
	{"x":417, "y":718},
	{"x":417, "y":719},
	{"x":417, "y":720},
	{"x":418, "y":718},
	{"x":418, "y":719},
	{"x":418, "y":720},
	{"x":419, "y":718},
	{"x":419, "y":719},
	{"x":419, "y":720},
	{"x":420, "y":718},
	{"x":420, "y":719},
	{"x":420, "y":720},
	{"x":421, "y":718},
	{"x":421, "y":719},
	{"x":421, "y":720},
	{"x":422, "y":718},
	{"x":422, "y":719},
	{"x":422, "y":720},
	{"x":423, "y":718},
	{"x":423, "y":719},
	{"x":423, "y":720},
	{"x":424, "y":718},
	{"x":424, "y":719},
	{"x":424, "y":720},
	{"x":425, "y":718},
	{"x":425, "y":719},
	{"x":425, "y":720},
	{"x":426, "y":718},
	{"x":426, "y":719},
	{"x":426, "y":720},
	{"x":427, "y":717},
	{"x":427, "y":718},
	{"x":427, "y":719},
	{"x":428, "y":717},
	{"x":428, "y":718},
	{"x":428, "y":719},
	{"x":429, "y":717},
	{"x":429, "y":718},
	{"x":429, "y":719},
	{"x":430, "y":717},
	{"x":430, "y":718},
	{"x":430, "y":719},
	{"x":431, "y":717},
	{"x":431, "y":718},
	{"x":431, "y":719},
	{"x":432, "y":717},
	{"x":432, "y":718},
	{"x":432, "y":719},
	{"x":433, "y":717},
	{"x":433, "y":718},
	{"x":433, "y":719},
	{"x":434, "y":717},
	{"x":434, "y":718},
	{"x":434, "y":719},
	{"x":435, "y":717},
	{"x":435, "y":718},
	{"x":435, "y":719},
	{"x":436, "y":717},
	{"x":436, "y":718},
	{"x":436, "y":719},
	{"x":437, "y":716},
	{"x":437, "y":717},
	{"x":437, "y":718},
	{"x":437, "y":719},
	{"x":438, "y":715},
	{"x":438, "y":716},
	{"x":438, "y":717},
	{"x":438, "y":718},
	{"x":439, "y":714},
	{"x":439, "y":715},
	{"x":439, "y":716},
	{"x":439, "y":717},
	{"x":440, "y":714},
	{"x":440, "y":715},
	{"x":440, "y":716},
	{"x":441, "y":713},
	{"x":441, "y":714},
	{"x":441, "y":715},
	{"x":441, "y":716},
	{"x":442, "y":712},
	{"x":442, "y":713},
	{"x":442, "y":714},
	{"x":442, "y":715},
	{"x":443, "y":711},
	{"x":443, "y":712},
	{"x":443, "y":713},
	{"x":443, "y":714},
	{"x":444, "y":710},
	{"x":444, "y":711},
	{"x":444, "y":712},
	{"x":444, "y":713},
	{"x":445, "y":710},
	{"x":445, "y":711},
	{"x":445, "y":712},
	{"x":446, "y":709},
	{"x":446, "y":710},
	{"x":446, "y":711},
	{"x":446, "y":712},
	{"x":447, "y":708},
	{"x":447, "y":709},
	{"x":447, "y":710},
	{"x":447, "y":711},
	{"x":448, "y":707},
	{"x":448, "y":708},
	{"x":448, "y":709},
	{"x":448, "y":710},
	{"x":449, "y":707},
	{"x":449, "y":708},
	{"x":449, "y":709},
	{"x":450, "y":706},
	{"x":450, "y":707},
	{"x":450, "y":708},
	{"x":450, "y":709},
	{"x":451, "y":705},
	{"x":451, "y":706},
	{"x":451, "y":707},
	{"x":451, "y":708},
	{"x":452, "y":704},
	{"x":452, "y":705},
	{"x":452, "y":706},
	{"x":452, "y":707},
	{"x":453, "y":703},
	{"x":453, "y":704},
	{"x":453, "y":705},
	{"x":453, "y":706},
	{"x":454, "y":703},
	{"x":454, "y":704},
	{"x":454, "y":705},
	{"x":454, "y":706},
	{"x":455, "y":702},
	{"x":455, "y":703},
	{"x":455, "y":704},
	{"x":455, "y":705},
	{"x":456, "y":701},
	{"x":456, "y":702},
	{"x":456, "y":703},
	{"x":456, "y":704},
	{"x":457, "y":700},
	{"x":457, "y":701},
	{"x":457, "y":702},
	{"x":457, "y":703},
	{"x":458, "y":700},
	{"x":458, "y":701},
	{"x":458, "y":702},
	{"x":459, "y":699},
	{"x":459, "y":700},
	{"x":459, "y":701},
	{"x":459, "y":702},
	{"x":460, "y":698},
	{"x":460, "y":699},
	{"x":460, "y":700},
	{"x":460, "y":701},
	{"x":461, "y":697},
	{"x":461, "y":698},
	{"x":461, "y":699},
	{"x":461, "y":700},
	{"x":462, "y":697},
	{"x":462, "y":698},
	{"x":462, "y":699},
	{"x":463, "y":696},
	{"x":463, "y":697},
	{"x":463, "y":698},
	{"x":463, "y":699},
	{"x":464, "y":695},
	{"x":464, "y":696},
	{"x":464, "y":697},
	{"x":464, "y":698},
	{"x":465, "y":694},
	{"x":465, "y":695},
	{"x":465, "y":696},
	{"x":465, "y":697},
	{"x":466, "y":693},
	{"x":466, "y":694},
	{"x":466, "y":695},
	{"x":466, "y":696},
	{"x":467, "y":693},
	{"x":467, "y":694},
	{"x":467, "y":695},
	{"x":468, "y":692},
	{"x":468, "y":693},
	{"x":468, "y":694},
	{"x":468, "y":695},
	{"x":469, "y":691},
	{"x":469, "y":692},
	{"x":469, "y":693},
	{"x":469, "y":694},
	{"x":470, "y":690},
	{"x":470, "y":691},
	{"x":470, "y":692},
	{"x":470, "y":693},
	{"x":471, "y":687},
	{"x":471, "y":688},
	{"x":471, "y":689},
	{"x":471, "y":690},
	{"x":471, "y":691},
	{"x":471, "y":692},
	{"x":472, "y":685},
	{"x":472, "y":686},
	{"x":472, "y":687},
	{"x":472, "y":688},
	{"x":472, "y":689},
	{"x":472, "y":690},
	{"x":472, "y":691},
	{"x":472, "y":692},
	{"x":473, "y":682},
	{"x":473, "y":683},
	{"x":473, "y":684},
	{"x":473, "y":685},
	{"x":473, "y":686},
	{"x":473, "y":687},
	{"x":473, "y":688},
	{"x":473, "y":689},
	{"x":474, "y":679},
	{"x":474, "y":680},
	{"x":474, "y":681},
	{"x":474, "y":682},
	{"x":474, "y":683},
	{"x":474, "y":684},
	{"x":474, "y":685},
	{"x":474, "y":686},
	{"x":474, "y":687},
	{"x":475, "y":676},
	{"x":475, "y":677},
	{"x":475, "y":678},
	{"x":475, "y":679},
	{"x":475, "y":680},
	{"x":475, "y":681},
	{"x":475, "y":682},
	{"x":475, "y":683},
	{"x":475, "y":684},
	{"x":476, "y":674},
	{"x":476, "y":675},
	{"x":476, "y":676},
	{"x":476, "y":677},
	{"x":476, "y":678},
	{"x":476, "y":679},
	{"x":476, "y":680},
	{"x":476, "y":681},
	{"x":477, "y":671},
	{"x":477, "y":672},
	{"x":477, "y":673},
	{"x":477, "y":674},
	{"x":477, "y":675},
	{"x":477, "y":676},
	{"x":477, "y":677},
	{"x":477, "y":678},
	{"x":477, "y":679},
	{"x":478, "y":668},
	{"x":478, "y":669},
	{"x":478, "y":670},
	{"x":478, "y":671},
	{"x":478, "y":672},
	{"x":478, "y":673},
	{"x":478, "y":674},
	{"x":478, "y":675},
	{"x":478, "y":676},
	{"x":479, "y":666},
	{"x":479, "y":667},
	{"x":479, "y":668},
	{"x":479, "y":669},
	{"x":479, "y":670},
	{"x":479, "y":671},
	{"x":479, "y":672},
	{"x":479, "y":673},
	{"x":480, "y":663},
	{"x":480, "y":664},
	{"x":480, "y":665},
	{"x":480, "y":666},
	{"x":480, "y":667},
	{"x":480, "y":668},
	{"x":480, "y":669},
	{"x":480, "y":670},
	{"x":480, "y":671},
	{"x":481, "y":660},
	{"x":481, "y":661},
	{"x":481, "y":662},
	{"x":481, "y":663},
	{"x":481, "y":664},
	{"x":481, "y":665},
	{"x":481, "y":666},
	{"x":481, "y":667},
	{"x":481, "y":668},
	{"x":482, "y":658},
	{"x":482, "y":659},
	{"x":482, "y":660},
	{"x":482, "y":661},
	{"x":482, "y":662},
	{"x":482, "y":663},
	{"x":482, "y":664},
	{"x":482, "y":665},
	{"x":483, "y":655},
	{"x":483, "y":656},
	{"x":483, "y":657},
	{"x":483, "y":658},
	{"x":483, "y":659},
	{"x":483, "y":660},
	{"x":483, "y":661},
	{"x":483, "y":662},
	{"x":483, "y":663},
	{"x":484, "y":652},
	{"x":484, "y":653},
	{"x":484, "y":654},
	{"x":484, "y":655},
	{"x":484, "y":656},
	{"x":484, "y":657},
	{"x":484, "y":658},
	{"x":484, "y":659},
	{"x":484, "y":660},
	{"x":485, "y":650},
	{"x":485, "y":651},
	{"x":485, "y":652},
	{"x":485, "y":653},
	{"x":485, "y":654},
	{"x":485, "y":655},
	{"x":485, "y":656},
	{"x":485, "y":657},
	{"x":486, "y":647},
	{"x":486, "y":648},
	{"x":486, "y":649},
	{"x":486, "y":650},
	{"x":486, "y":651},
	{"x":486, "y":652},
	{"x":486, "y":653},
	{"x":486, "y":654},
	{"x":487, "y":644},
	{"x":487, "y":645},
	{"x":487, "y":646},
	{"x":487, "y":647},
	{"x":487, "y":648},
	{"x":487, "y":649},
	{"x":487, "y":650},
	{"x":487, "y":651},
	{"x":487, "y":652},
	{"x":488, "y":642},
	{"x":488, "y":643},
	{"x":488, "y":644},
	{"x":488, "y":645},
	{"x":488, "y":646},
	{"x":488, "y":647},
	{"x":488, "y":648},
	{"x":488, "y":649},
	{"x":489, "y":639},
	{"x":489, "y":640},
	{"x":489, "y":641},
	{"x":489, "y":642},
	{"x":489, "y":643},
	{"x":489, "y":644},
	{"x":489, "y":645},
	{"x":489, "y":646},
	{"x":490, "y":638},
	{"x":490, "y":639},
	{"x":490, "y":640},
	{"x":490, "y":641},
	{"x":490, "y":642},
	{"x":490, "y":643},
	{"x":490, "y":644},
	{"x":491, "y":637},
	{"x":491, "y":638},
	{"x":491, "y":639},
	{"x":491, "y":640},
	{"x":491, "y":641},
	{"x":492, "y":636},
	{"x":492, "y":637},
	{"x":492, "y":638},
	{"x":492, "y":639},
	{"x":492, "y":640},
	{"x":493, "y":635},
	{"x":493, "y":636},
	{"x":493, "y":637},
	{"x":493, "y":638},
	{"x":494, "y":634},
	{"x":494, "y":635},
	{"x":494, "y":636},
	{"x":494, "y":637},
	{"x":495, "y":633},
	{"x":495, "y":634},
	{"x":495, "y":635},
	{"x":495, "y":636},
	{"x":496, "y":632},
	{"x":496, "y":633},
	{"x":496, "y":634},
	{"x":496, "y":635},
	{"x":497, "y":631},
	{"x":497, "y":632},
	{"x":497, "y":633},
	{"x":497, "y":634},
	{"x":498, "y":630},
	{"x":498, "y":631},
	{"x":498, "y":632},
	{"x":498, "y":633},
	{"x":499, "y":629},
	{"x":499, "y":630},
	{"x":499, "y":631},
	{"x":499, "y":632},
	{"x":500, "y":628},
	{"x":500, "y":629},
	{"x":500, "y":630},
	{"x":500, "y":631},
	{"x":501, "y":626},
	{"x":501, "y":627},
	{"x":501, "y":628},
	{"x":501, "y":629},
	{"x":501, "y":630},
	{"x":502, "y":625},
	{"x":502, "y":626},
	{"x":502, "y":627},
	{"x":502, "y":628},
	{"x":502, "y":629},
	{"x":503, "y":625},
	{"x":503, "y":626},
	{"x":503, "y":627},
	{"x":503, "y":628},
	{"x":504, "y":625},
	{"x":504, "y":626},
	{"x":504, "y":627},
	{"x":505, "y":625},
	{"x":505, "y":626},
	{"x":505, "y":627},
	{"x":506, "y":625},
	{"x":506, "y":626},
	{"x":506, "y":627},
	{"x":507, "y":625},
	{"x":507, "y":626},
	{"x":507, "y":627},
	{"x":508, "y":625},
	{"x":508, "y":626},
	{"x":508, "y":627},
	{"x":509, "y":625},
	{"x":509, "y":626},
	{"x":509, "y":627},
	{"x":510, "y":625},
	{"x":510, "y":626},
	{"x":510, "y":627},
	{"x":511, "y":626},
	{"x":511, "y":627},
	{"x":511, "y":628},
	{"x":512, "y":626},
	{"x":512, "y":627},
	{"x":512, "y":628},
	{"x":513, "y":626},
	{"x":513, "y":627},
	{"x":513, "y":628},
	{"x":514, "y":626},
	{"x":514, "y":627},
	{"x":514, "y":628},
	{"x":515, "y":624},
	{"x":515, "y":625},
	{"x":515, "y":626},
	{"x":515, "y":627},
	{"x":515, "y":628},
	{"x":516, "y":624},
	{"x":516, "y":625},
	{"x":516, "y":626},
	{"x":516, "y":627},
	{"x":516, "y":628},
	{"x":517, "y":624},
	{"x":517, "y":625},
	{"x":517, "y":626},
	{"x":517, "y":627},
	{"x":517, "y":628},
	{"x":518, "y":625},
	{"x":518, "y":626},
	{"x":518, "y":627},
	{"x":518, "y":628},
	{"x":519, "y":626},
	{"x":519, "y":627},
	{"x":519, "y":628},
	{"x":519, "y":629},
	{"x":520, "y":627},
	{"x":520, "y":628},
	{"x":520, "y":629},
	{"x":520, "y":630},
	{"x":521, "y":628},
	{"x":521, "y":629},
	{"x":521, "y":630},
	{"x":521, "y":631},
	{"x":522, "y":629},
	{"x":522, "y":630},
	{"x":522, "y":631},
	{"x":523, "y":629},
	{"x":523, "y":630},
	{"x":523, "y":631},
	{"x":523, "y":632},
	{"x":524, "y":630},
	{"x":524, "y":631},
	{"x":524, "y":632},
	{"x":524, "y":633},
	{"x":525, "y":631},
	{"x":525, "y":632},
	{"x":525, "y":633},
	{"x":525, "y":634},
	{"x":526, "y":632},
	{"x":526, "y":633},
	{"x":526, "y":634},
	{"x":526, "y":635},
	{"x":527, "y":633},
	{"x":527, "y":634},
	{"x":527, "y":635},
	{"x":527, "y":636},
	{"x":528, "y":634},
	{"x":528, "y":635},
	{"x":528, "y":636},
	{"x":528, "y":637},
	{"x":529, "y":634},
	{"x":529, "y":635},
	{"x":529, "y":636},
	{"x":529, "y":637},
	{"x":530, "y":635},
	{"x":530, "y":636},
	{"x":530, "y":637},
	{"x":530, "y":638},
	{"x":531, "y":636},
	{"x":531, "y":637},
	{"x":531, "y":638},
	{"x":531, "y":639},
	{"x":532, "y":637},
	{"x":532, "y":638},
	{"x":532, "y":639},
	{"x":532, "y":640},
	{"x":533, "y":638},
	{"x":533, "y":639},
	{"x":533, "y":640},
	{"x":533, "y":641},
	{"x":534, "y":639},
	{"x":534, "y":640},
	{"x":534, "y":641},
	{"x":534, "y":642},
	{"x":535, "y":639},
	{"x":535, "y":640},
	{"x":535, "y":641},
	{"x":535, "y":642},
	{"x":536, "y":640},
	{"x":536, "y":641},
	{"x":536, "y":642},
	{"x":536, "y":643},
	{"x":537, "y":641},
	{"x":537, "y":642},
	{"x":537, "y":643},
	{"x":537, "y":644},
	{"x":538, "y":642},
	{"x":538, "y":643},
	{"x":538, "y":644},
	{"x":538, "y":645},
	{"x":539, "y":643},
	{"x":539, "y":644},
	{"x":539, "y":645},
	{"x":539, "y":646},
	{"x":540, "y":644},
	{"x":540, "y":645},
	{"x":540, "y":646},
	{"x":540, "y":647},
	{"x":541, "y":645},
	{"x":541, "y":646},
	{"x":541, "y":647},
	{"x":542, "y":645},
	{"x":542, "y":646},
	{"x":542, "y":647},
	{"x":542, "y":648},
	{"x":543, "y":646},
	{"x":543, "y":647},
	{"x":543, "y":648},
	{"x":543, "y":649},
	{"x":544, "y":647},
	{"x":544, "y":648},
	{"x":544, "y":649},
	{"x":544, "y":650},
	{"x":545, "y":648},
	{"x":545, "y":649},
	{"x":545, "y":650},
	{"x":545, "y":651},
	{"x":546, "y":649},
	{"x":546, "y":650},
	{"x":546, "y":651},
	{"x":546, "y":652},
	{"x":547, "y":650},
	{"x":547, "y":651},
	{"x":547, "y":652},
	{"x":548, "y":650},
	{"x":548, "y":651},
	{"x":548, "y":652},
	{"x":548, "y":653},
	{"x":549, "y":651},
	{"x":549, "y":652},
	{"x":549, "y":653},
	{"x":549, "y":654},
	{"x":550, "y":652},
	{"x":550, "y":653},
	{"x":550, "y":654},
	{"x":550, "y":655},
	{"x":551, "y":653},
	{"x":551, "y":654},
	{"x":551, "y":655},
	{"x":551, "y":656},
	{"x":552, "y":654},
	{"x":552, "y":655},
	{"x":552, "y":656},
	{"x":552, "y":657},
	{"x":553, "y":655},
	{"x":553, "y":656},
	{"x":553, "y":657},
	{"x":554, "y":655},
	{"x":554, "y":656},
	{"x":554, "y":657},
	{"x":554, "y":658},
	{"x":555, "y":656},
	{"x":555, "y":657},
	{"x":555, "y":658},
	{"x":555, "y":659},
	{"x":556, "y":657},
	{"x":556, "y":658},
	{"x":556, "y":659},
	{"x":556, "y":660},
	{"x":557, "y":658},
	{"x":557, "y":659},
	{"x":557, "y":660},
	{"x":557, "y":661},
	{"x":558, "y":659},
	{"x":558, "y":660},
	{"x":558, "y":661},
	{"x":558, "y":662},
	{"x":559, "y":660},
	{"x":559, "y":661},
	{"x":559, "y":662},
	{"x":559, "y":663},
	{"x":560, "y":660},
	{"x":560, "y":661},
	{"x":560, "y":662},
	{"x":560, "y":663},
	{"x":561, "y":661},
	{"x":561, "y":662},
	{"x":561, "y":663},
	{"x":561, "y":664},
	{"x":562, "y":662},
	{"x":562, "y":663},
	{"x":562, "y":664},
	{"x":562, "y":665},
	{"x":563, "y":663},
	{"x":563, "y":664},
	{"x":563, "y":665},
	{"x":563, "y":666},
	{"x":564, "y":664},
	{"x":564, "y":665},
	{"x":564, "y":666},
	{"x":564, "y":667},
	{"x":565, "y":665},
	{"x":565, "y":666},
	{"x":565, "y":667},
	{"x":565, "y":668},
	{"x":566, "y":665},
	{"x":566, "y":666},
	{"x":566, "y":667},
	{"x":566, "y":668},
	{"x":567, "y":666},
	{"x":567, "y":667},
	{"x":567, "y":668},
	{"x":567, "y":669},
	{"x":568, "y":667},
	{"x":568, "y":668},
	{"x":568, "y":669},
	{"x":568, "y":670},
	{"x":569, "y":668},
	{"x":569, "y":669},
	{"x":569, "y":670},
	{"x":569, "y":671},
	{"x":570, "y":669},
	{"x":570, "y":670},
	{"x":570, "y":671},
	{"x":570, "y":672},
	{"x":571, "y":670},
	{"x":571, "y":671},
	{"x":571, "y":672},
	{"x":571, "y":673},
	{"x":572, "y":670},
	{"x":572, "y":671},
	{"x":572, "y":672},
	{"x":572, "y":673},
	{"x":573, "y":671},
	{"x":573, "y":672},
	{"x":573, "y":673},
	{"x":573, "y":674},
	{"x":574, "y":672},
	{"x":574, "y":673},
	{"x":574, "y":674},
	{"x":574, "y":675},
	{"x":575, "y":673},
	{"x":575, "y":674},
	{"x":575, "y":675},
	{"x":575, "y":676},
	{"x":576, "y":674},
	{"x":576, "y":675},
	{"x":576, "y":676},
	{"x":576, "y":677},
	{"x":577, "y":675},
	{"x":577, "y":676},
	{"x":577, "y":677},
	{"x":577, "y":678},
	{"x":578, "y":676},
	{"x":578, "y":677},
	{"x":578, "y":678},
	{"x":579, "y":676},
	{"x":579, "y":677},
	{"x":579, "y":678},
	{"x":579, "y":679},
	{"x":580, "y":677},
	{"x":580, "y":678},
	{"x":580, "y":679},
	{"x":580, "y":680},
	{"x":581, "y":678},
	{"x":581, "y":679},
	{"x":581, "y":680},
	{"x":581, "y":681},
	{"x":582, "y":679},
	{"x":582, "y":680},
	{"x":582, "y":681},
	{"x":582, "y":682},
	{"x":583, "y":680},
	{"x":583, "y":681},
	{"x":583, "y":682},
	{"x":583, "y":683},
	{"x":584, "y":681},
	{"x":584, "y":682},
	{"x":584, "y":683},
	{"x":585, "y":681},
	{"x":585, "y":682},
	{"x":585, "y":683},
	{"x":585, "y":684},
	{"x":586, "y":682},
	{"x":586, "y":683},
	{"x":586, "y":684},
	{"x":586, "y":685},
	{"x":587, "y":683},
	{"x":587, "y":684},
	{"x":587, "y":685},
	{"x":587, "y":686},
	{"x":588, "y":684},
	{"x":588, "y":685},
	{"x":588, "y":686},
	{"x":588, "y":687},
	{"x":589, "y":685},
	{"x":589, "y":686},
	{"x":589, "y":687},
	{"x":589, "y":688},
	{"x":590, "y":686},
	{"x":590, "y":687},
	{"x":590, "y":688},
	{"x":591, "y":686},
	{"x":591, "y":687},
	{"x":591, "y":688},
	{"x":591, "y":689},
	{"x":592, "y":687},
	{"x":592, "y":688},
	{"x":592, "y":689},
	{"x":592, "y":690},
	{"x":593, "y":688},
	{"x":593, "y":689},
	{"x":593, "y":690},
	{"x":593, "y":691},
	{"x":594, "y":689},
	{"x":594, "y":690},
	{"x":594, "y":691},
	{"x":594, "y":692},
	{"x":595, "y":690},
	{"x":595, "y":691},
	{"x":595, "y":692},
	{"x":595, "y":693},
	{"x":596, "y":691},
	{"x":596, "y":692},
	{"x":596, "y":693},
	{"x":596, "y":694},
	{"x":597, "y":691},
	{"x":597, "y":692},
	{"x":597, "y":693},
	{"x":597, "y":694},
	{"x":598, "y":692},
	{"x":598, "y":693},
	{"x":598, "y":694},
	{"x":598, "y":695},
	{"x":599, "y":693},
	{"x":599, "y":694},
	{"x":599, "y":695},
	{"x":599, "y":696},
	{"x":600, "y":694},
	{"x":600, "y":695},
	{"x":600, "y":696},
	{"x":600, "y":697},
	{"x":601, "y":695},
	{"x":601, "y":696},
	{"x":601, "y":697},
	{"x":601, "y":698},
	{"x":602, "y":696},
	{"x":602, "y":697},
	{"x":602, "y":698},
	{"x":602, "y":699},
	{"x":603, "y":696},
	{"x":603, "y":697},
	{"x":603, "y":698},
	{"x":603, "y":699},
	{"x":604, "y":697},
	{"x":604, "y":698},
	{"x":604, "y":699},
	{"x":604, "y":700},
	{"x":605, "y":698},
	{"x":605, "y":699},
	{"x":605, "y":700},
	{"x":605, "y":701},
	{"x":606, "y":699},
	{"x":606, "y":700},
	{"x":606, "y":701},
	{"x":606, "y":702},
	{"x":607, "y":700},
	{"x":607, "y":701},
	{"x":607, "y":702},
	{"x":607, "y":703},
	{"x":608, "y":701},
	{"x":608, "y":702},
	{"x":608, "y":703},
	{"x":608, "y":704},
	{"x":609, "y":702},
	{"x":609, "y":703},
	{"x":609, "y":704},
	{"x":610, "y":702},
	{"x":610, "y":703},
	{"x":610, "y":704},
	{"x":610, "y":705},
	{"x":611, "y":703},
	{"x":611, "y":704},
	{"x":611, "y":705},
	{"x":611, "y":706},
	{"x":612, "y":704},
	{"x":612, "y":705},
	{"x":612, "y":706},
	{"x":612, "y":707},
	{"x":613, "y":705},
	{"x":613, "y":706},
	{"x":613, "y":707},
	{"x":613, "y":708},
	{"x":614, "y":706},
	{"x":614, "y":707},
	{"x":614, "y":708},
	{"x":614, "y":709},
	{"x":615, "y":707},
	{"x":615, "y":708},
	{"x":615, "y":709},
	{"x":616, "y":707},
	{"x":616, "y":708},
	{"x":616, "y":709}
]}
